{
  "_meta": {
    "schema_version": "1.0",
    "description": "TCG (Tool Capability Graph) default seed for ChatAgentLoop v4. Source of truth for tool selection. Runtime augmentation is forbidden - new tools are learned through reinforcement.",
    "schema_notes": {
      "node_kinds": {
        "TCGTool": "An MCP tool. properties: governance_tier ∈ {GREEN,YELLOW,RED}, side_effect ∈ {read,write,net,compute,destructive}, category, latency_tier ∈ {fast,medium,slow}, safe_for_prediction ∈ {true,false}",
        "TCGIntent": "A user-intent classification. properties: keywords (list), preferred_sequence (list of tool_ids)",
        "TCGWorkflowPattern": "A learned or seeded sequence. properties: tool_sequence (list), support_count (int), graduated (bool), intent_id",
        "TCGLesson": "A past mistake pattern. properties: severity, hit_count"
      },
      "edge_kinds": {
        "USED_AFTER": "tool A is observed after tool B in successful sequences",
        "MATCHES_INTENT": "tool is relevant to intent",
        "PART_OF": "tool is part of workflow pattern",
        "CAUSED_BY": "lesson applies to tool"
      },
      "weight_range": [
        0.0,
        10.0
      ],
      "probation_thresholds": {
        "min_observations": 3,
        "min_holdouts": 2,
        "novelty_lift_min": 0.2
      }
    }
  },
  "nodes": {
    "tool_graq_read": {
      "id": "tool_graq_read",
      "label": "graq_read",
      "entity_type": "TCGTool",
      "description": "Read file contents from disk with line numbers. Safe, idempotent, no side effects",
      "properties": {
        "governance_tier": "GREEN",
        "side_effect": "read",
        "category": "filesystem",
        "latency_tier": "fast",
        "safe_for_prediction": true
      }
    },
    "tool_graq_glob": {
      "id": "tool_graq_glob",
      "label": "graq_glob",
      "entity_type": "TCGTool",
      "description": "Find files matching a glob pattern. Safe, idempotent",
      "properties": {
        "governance_tier": "GREEN",
        "side_effect": "read",
        "category": "filesystem",
        "latency_tier": "fast",
        "safe_for_prediction": true
      }
    },
    "tool_graq_grep": {
      "id": "tool_graq_grep",
      "label": "graq_grep",
      "entity_type": "TCGTool",
      "description": "Search file contents by regex. Safe, idempotent",
      "properties": {
        "governance_tier": "GREEN",
        "side_effect": "read",
        "category": "filesystem",
        "latency_tier": "fast",
        "safe_for_prediction": true
      }
    },
    "tool_graq_context": {
      "id": "tool_graq_context",
      "label": "graq_context",
      "entity_type": "TCGTool",
      "description": "Activate KG context for a task. Returns focused nodes + lessons. The preferred grounding step before reasoning",
      "properties": {
        "governance_tier": "GREEN",
        "side_effect": "read",
        "category": "kg",
        "latency_tier": "medium",
        "safe_for_prediction": true
      }
    },
    "tool_graq_inspect": {
      "id": "tool_graq_inspect",
      "label": "graq_inspect",
      "entity_type": "TCGTool",
      "description": "Inspect graph stats or a node. Safe, read-only",
      "properties": {
        "governance_tier": "GREEN",
        "side_effect": "read",
        "category": "kg",
        "latency_tier": "fast",
        "safe_for_prediction": true
      }
    },
    "tool_graq_lessons": {
      "id": "tool_graq_lessons",
      "label": "graq_lessons",
      "entity_type": "TCGTool",
      "description": "Retrieve lessons for an operation. Read-only",
      "properties": {
        "governance_tier": "GREEN",
        "side_effect": "read",
        "category": "kg",
        "latency_tier": "fast",
        "safe_for_prediction": true
      }
    },
    "tool_graq_impact": {
      "id": "tool_graq_impact",
      "label": "graq_impact",
      "entity_type": "TCGTool",
      "description": "Trace the blast radius of a component change",
      "properties": {
        "governance_tier": "GREEN",
        "side_effect": "read",
        "category": "kg",
        "latency_tier": "medium",
        "safe_for_prediction": true
      }
    },
    "tool_graq_preflight": {
      "id": "tool_graq_preflight",
      "label": "graq_preflight",
      "entity_type": "TCGTool",
      "description": "Governance preflight before a change. Returns lessons + ADRs + safety boundaries",
      "properties": {
        "governance_tier": "GREEN",
        "side_effect": "read",
        "category": "governance",
        "latency_tier": "medium",
        "safe_for_prediction": true
      }
    },
    "tool_graq_reason": {
      "id": "tool_graq_reason",
      "label": "graq_reason",
      "entity_type": "TCGTool",
      "description": "Run graph-of-agents reasoning over the KG. Use before design / architectural decisions",
      "properties": {
        "governance_tier": "GREEN",
        "side_effect": "compute",
        "category": "reasoning",
        "latency_tier": "slow",
        "safe_for_prediction": true
      }
    },
    "tool_graq_reason_batch": {
      "id": "tool_graq_reason_batch",
      "label": "graq_reason_batch",
      "entity_type": "TCGTool",
      "description": "Run multiple reasoning queries in parallel. Used by ChatAgentLoop v4 debate subsystem",
      "properties": {
        "governance_tier": "GREEN",
        "side_effect": "compute",
        "category": "reasoning",
        "latency_tier": "slow",
        "safe_for_prediction": true
      }
    },
    "tool_graq_predict": {
      "id": "tool_graq_predict",
      "label": "graq_predict",
      "entity_type": "TCGTool",
      "description": "Governed compound prediction that may fold a new subgraph into the KG",
      "properties": {
        "governance_tier": "YELLOW",
        "side_effect": "write",
        "category": "reasoning",
        "latency_tier": "slow",
        "safe_for_prediction": true
      }
    },
    "tool_graq_review": {
      "id": "tool_graq_review",
      "label": "graq_review",
      "entity_type": "TCGTool",
      "description": "Governed review of a file, diff, or spec. Returns BLOCKER/MAJOR/MINOR findings",
      "properties": {
        "governance_tier": "GREEN",
        "side_effect": "read",
        "category": "reasoning",
        "latency_tier": "slow",
        "safe_for_prediction": true
      }
    },
    "tool_graq_generate": {
      "id": "tool_graq_generate",
      "label": "graq_generate",
      "entity_type": "TCGTool",
      "description": "Governed code generation. Produces a unified diff. THE preferred codegen tool — top of the list for codegen intent",
      "properties": {
        "governance_tier": "YELLOW",
        "side_effect": "compute",
        "category": "codegen",
        "latency_tier": "slow",
        "safe_for_prediction": true
      }
    },
    "tool_graq_edit": {
      "id": "tool_graq_edit",
      "label": "graq_edit",
      "entity_type": "TCGTool",
      "description": "Governed atomic file edit. Default dry_run=True. Use on small / low-risk files",
      "properties": {
        "governance_tier": "YELLOW",
        "side_effect": "write",
        "category": "codegen",
        "latency_tier": "slow",
        "safe_for_prediction": true
      }
    },
    "tool_graq_apply": {
      "id": "tool_graq_apply",
      "label": "graq_apply",
      "entity_type": "TCGTool",
      "description": "Deterministic anchor-based bytes.replace insertion. Use on hub files (impact radius > 20 or > 1500 lines)",
      "properties": {
        "governance_tier": "YELLOW",
        "side_effect": "write",
        "category": "codegen",
        "latency_tier": "medium",
        "safe_for_prediction": true
      }
    },
    "tool_graq_write": {
      "id": "tool_graq_write",
      "label": "graq_write",
      "entity_type": "TCGTool",
      "description": "Governed atomic file write. Default dry_run=True. Creates new files",
      "properties": {
        "governance_tier": "YELLOW",
        "side_effect": "write",
        "category": "filesystem",
        "latency_tier": "fast",
        "safe_for_prediction": true
      }
    },
    "tool_graq_bash": {
      "id": "tool_graq_bash",
      "label": "graq_bash",
      "entity_type": "TCGTool",
      "description": "Run a shell command in the project directory. Governed — blocked in read-only mode",
      "properties": {
        "governance_tier": "RED",
        "side_effect": "destructive",
        "category": "shell",
        "latency_tier": "medium",
        "safe_for_prediction": false
      }
    },
    "tool_graq_test": {
      "id": "tool_graq_test",
      "label": "graq_test",
      "entity_type": "TCGTool",
      "description": "Run pytest on a target and parse results. Use focused paths",
      "properties": {
        "governance_tier": "YELLOW",
        "side_effect": "compute",
        "category": "test",
        "latency_tier": "slow",
        "safe_for_prediction": true
      }
    },
    "tool_graq_git_status": {
      "id": "tool_graq_git_status",
      "label": "graq_git_status",
      "entity_type": "TCGTool",
      "description": "Git working tree status. Read-only",
      "properties": {
        "governance_tier": "GREEN",
        "side_effect": "read",
        "category": "git",
        "latency_tier": "fast",
        "safe_for_prediction": true
      }
    },
    "tool_graq_git_diff": {
      "id": "tool_graq_git_diff",
      "label": "graq_git_diff",
      "entity_type": "TCGTool",
      "description": "Git diff. Read-only",
      "properties": {
        "governance_tier": "GREEN",
        "side_effect": "read",
        "category": "git",
        "latency_tier": "fast",
        "safe_for_prediction": true
      }
    },
    "tool_graq_git_log": {
      "id": "tool_graq_git_log",
      "label": "graq_git_log",
      "entity_type": "TCGTool",
      "description": "Git log. Read-only",
      "properties": {
        "governance_tier": "GREEN",
        "side_effect": "read",
        "category": "git",
        "latency_tier": "fast",
        "safe_for_prediction": true
      }
    },
    "tool_graq_git_branch": {
      "id": "tool_graq_git_branch",
      "label": "graq_git_branch",
      "entity_type": "TCGTool",
      "description": "List / create / switch git branches",
      "properties": {
        "governance_tier": "YELLOW",
        "side_effect": "write",
        "category": "git",
        "latency_tier": "fast",
        "safe_for_prediction": false
      }
    },
    "tool_graq_git_commit": {
      "id": "tool_graq_git_commit",
      "label": "graq_git_commit",
      "entity_type": "TCGTool",
      "description": "Governed git commit. Patent scan runs automatically",
      "properties": {
        "governance_tier": "RED",
        "side_effect": "destructive",
        "category": "git",
        "latency_tier": "medium",
        "safe_for_prediction": false
      }
    },
    "tool_graq_debug": {
      "id": "tool_graq_debug",
      "label": "graq_debug",
      "entity_type": "TCGTool",
      "description": "Diagnostic triage over the KG. Helps localize bugs",
      "properties": {
        "governance_tier": "GREEN",
        "side_effect": "read",
        "category": "reasoning",
        "latency_tier": "medium",
        "safe_for_prediction": true
      }
    },
    "tool_graq_learn": {
      "id": "tool_graq_learn",
      "label": "graq_learn",
      "entity_type": "TCGTool",
      "description": "Teach the KG: record outcomes, entities, or knowledge. Writes new nodes/edges",
      "properties": {
        "governance_tier": "YELLOW",
        "side_effect": "write",
        "category": "kg",
        "latency_tier": "medium",
        "safe_for_prediction": true
      }
    },
    "tool_graq_scaffold": {
      "id": "tool_graq_scaffold",
      "label": "graq_scaffold",
      "entity_type": "TCGTool",
      "description": "Scaffold a new component from project conventions",
      "properties": {
        "governance_tier": "YELLOW",
        "side_effect": "compute",
        "category": "codegen",
        "latency_tier": "medium",
        "safe_for_prediction": true
      }
    },
    "tool_graq_gate": {
      "id": "tool_graq_gate",
      "label": "graq_gate",
      "entity_type": "TCGTool",
      "description": "Quality gate check on a change",
      "properties": {
        "governance_tier": "GREEN",
        "side_effect": "read",
        "category": "governance",
        "latency_tier": "medium",
        "safe_for_prediction": true
      }
    },
    "tool_graq_ingest": {
      "id": "tool_graq_ingest",
      "label": "graq_ingest",
      "entity_type": "TCGTool",
      "description": "Ingest external documents (PDF, DOCX) into the KG. Network + disk side effects",
      "properties": {
        "governance_tier": "RED",
        "side_effect": "destructive",
        "category": "ingestion",
        "latency_tier": "slow",
        "safe_for_prediction": false
      }
    },
    "tool_graq_vendor": {
      "id": "tool_graq_vendor",
      "label": "graq_vendor",
      "entity_type": "TCGTool",
      "description": "Vendor external dependencies into the repository",
      "properties": {
        "governance_tier": "RED",
        "side_effect": "destructive",
        "category": "dependencies",
        "latency_tier": "slow",
        "safe_for_prediction": false
      }
    },
    "tool_graq_reload": {
      "id": "tool_graq_reload",
      "label": "graq_reload",
      "entity_type": "TCGTool",
      "description": "Reload the KG from disk. Side effect: invalidates caches",
      "properties": {
        "governance_tier": "RED",
        "side_effect": "destructive",
        "category": "kg",
        "latency_tier": "medium",
        "safe_for_prediction": false
      }
    },
    "intent_codegen": {
      "id": "intent_codegen",
      "label": "codegen",
      "entity_type": "TCGIntent",
      "description": "User wants new code written (function, module, class)",
      "properties": {
        "keywords": [
          "write",
          "create",
          "implement",
          "function",
          "class",
          "module",
          "code"
        ],
        "preferred_sequence": [
          "tool_graq_context",
          "tool_graq_reason",
          "tool_graq_generate"
        ]
      }
    },
    "intent_bug_fix": {
      "id": "intent_bug_fix",
      "label": "bug_fix",
      "entity_type": "TCGIntent",
      "description": "User wants a bug diagnosed and fixed",
      "properties": {
        "keywords": [
          "fix",
          "bug",
          "error",
          "crash",
          "broken",
          "failing"
        ],
        "preferred_sequence": [
          "tool_graq_grep",
          "tool_graq_read",
          "tool_graq_debug",
          "tool_graq_generate"
        ]
      }
    },
    "intent_refactor": {
      "id": "intent_refactor",
      "label": "refactor",
      "entity_type": "TCGIntent",
      "description": "User wants code restructured without changing behavior",
      "properties": {
        "keywords": [
          "refactor",
          "restructure",
          "cleanup",
          "rename",
          "extract"
        ],
        "preferred_sequence": [
          "tool_graq_impact",
          "tool_graq_preflight",
          "tool_graq_generate"
        ]
      }
    },
    "intent_audit": {
      "id": "intent_audit",
      "label": "audit",
      "entity_type": "TCGIntent",
      "description": "User wants to audit or analyze existing code",
      "properties": {
        "keywords": [
          "audit",
          "analyze",
          "inspect",
          "trace",
          "impact"
        ],
        "preferred_sequence": [
          "tool_graq_inspect",
          "tool_graq_context",
          "tool_graq_impact"
        ]
      }
    },
    "intent_review": {
      "id": "intent_review",
      "label": "review",
      "entity_type": "TCGIntent",
      "description": "User wants a governed review of a file or diff",
      "properties": {
        "keywords": [
          "review",
          "critique",
          "check",
          "validate"
        ],
        "preferred_sequence": [
          "tool_graq_read",
          "tool_graq_review"
        ]
      }
    },
    "intent_explain": {
      "id": "intent_explain",
      "label": "explain",
      "entity_type": "TCGIntent",
      "description": "User wants an explanation of existing behavior",
      "properties": {
        "keywords": [
          "explain",
          "how does",
          "why does",
          "what is",
          "describe"
        ],
        "preferred_sequence": [
          "tool_graq_context",
          "tool_graq_reason"
        ]
      }
    },
    "intent_search": {
      "id": "intent_search",
      "label": "search",
      "entity_type": "TCGIntent",
      "description": "User wants to find something in the codebase",
      "properties": {
        "keywords": [
          "find",
          "where",
          "locate",
          "search",
          "grep"
        ],
        "preferred_sequence": [
          "tool_graq_glob",
          "tool_graq_grep"
        ]
      }
    },
    "intent_test": {
      "id": "intent_test",
      "label": "test",
      "entity_type": "TCGIntent",
      "description": "User wants tests written or executed",
      "properties": {
        "keywords": [
          "test",
          "pytest",
          "coverage",
          "assertion"
        ],
        "preferred_sequence": [
          "tool_graq_read",
          "tool_graq_generate",
          "tool_graq_test"
        ]
      }
    },
    "intent_write_new_artifact": {
      "id": "intent_write_new_artifact",
      "label": "write_new_artifact",
      "entity_type": "TCGIntent",
      "description": "User wants a new artifact (ADR, tracker entry, lesson) written — triggers convention_inference",
      "properties": {
        "keywords": [
          "write an ADR",
          "new adr",
          "hotfix tracker",
          "write a lesson",
          "new capability gap",
          "create a handoff"
        ],
        "preferred_sequence": [
          "tool_graq_glob",
          "tool_graq_read",
          "tool_graq_write"
        ]
      }
    },
    "intent_git_status": {
      "id": "intent_git_status",
      "label": "git_status",
      "entity_type": "TCGIntent",
      "description": "User wants to inspect git state",
      "properties": {
        "keywords": [
          "git status",
          "uncommitted",
          "staged",
          "branch"
        ],
        "preferred_sequence": [
          "tool_graq_git_status",
          "tool_graq_git_diff"
        ]
      }
    },
    "intent_commit": {
      "id": "intent_commit",
      "label": "commit",
      "entity_type": "TCGIntent",
      "description": "User wants to commit staged changes",
      "properties": {
        "keywords": [
          "commit",
          "git commit"
        ],
        "preferred_sequence": [
          "tool_graq_git_status",
          "tool_graq_git_diff",
          "tool_graq_git_commit"
        ]
      }
    },
    "intent_governed_refactor": {
      "id": "intent_governed_refactor",
      "label": "governed_refactor",
      "entity_type": "TCGIntent",
      "description": "User wants a refactor with full governance gating",
      "properties": {
        "keywords": [
          "governed refactor",
          "safe refactor"
        ],
        "preferred_sequence": [
          "tool_graq_git_branch",
          "tool_graq_impact",
          "tool_graq_preflight",
          "tool_graq_generate",
          "tool_graq_write",
          "tool_graq_test",
          "tool_graq_gate",
          "tool_graq_git_commit"
        ]
      }
    },
    "workflow_bug_fix": {
      "id": "workflow_bug_fix",
      "label": "bug_fix_workflow",
      "entity_type": "TCGWorkflowPattern",
      "description": "Bug fix workflow from mcp_dev_server workflow_plans (seeded, not mined)",
      "properties": {
        "tool_sequence": [
          "tool_graq_grep",
          "tool_graq_read",
          "tool_graq_debug",
          "tool_graq_generate",
          "tool_graq_write",
          "tool_graq_test",
          "tool_graq_git_commit",
          "tool_graq_learn"
        ],
        "support_count": 10,
        "graduated": true,
        "intent_id": "intent_bug_fix"
      }
    },
    "workflow_scaffold_and_test": {
      "id": "workflow_scaffold_and_test",
      "label": "scaffold_and_test_workflow",
      "entity_type": "TCGWorkflowPattern",
      "description": "Scaffold-and-test workflow from mcp_dev_server workflow_plans",
      "properties": {
        "tool_sequence": [
          "tool_graq_context",
          "tool_graq_scaffold",
          "tool_graq_write",
          "tool_graq_test",
          "tool_graq_learn"
        ],
        "support_count": 10,
        "graduated": true,
        "intent_id": "intent_codegen"
      }
    },
    "workflow_governed_refactor": {
      "id": "workflow_governed_refactor",
      "label": "governed_refactor_workflow",
      "entity_type": "TCGWorkflowPattern",
      "description": "Governed refactor workflow from mcp_dev_server workflow_plans",
      "properties": {
        "tool_sequence": [
          "tool_graq_git_branch",
          "tool_graq_impact",
          "tool_graq_preflight",
          "tool_graq_generate",
          "tool_graq_write",
          "tool_graq_test",
          "tool_graq_gate",
          "tool_graq_git_commit"
        ],
        "support_count": 10,
        "graduated": true,
        "intent_id": "intent_governed_refactor"
      }
    },
    "workflow_review_and_fix": {
      "id": "workflow_review_and_fix",
      "label": "review_and_fix_workflow",
      "entity_type": "TCGWorkflowPattern",
      "description": "Review-and-fix workflow from mcp_dev_server workflow_plans",
      "properties": {
        "tool_sequence": [
          "tool_graq_read",
          "tool_graq_review",
          "tool_graq_generate",
          "tool_graq_write",
          "tool_graq_test"
        ],
        "support_count": 10,
        "graduated": true,
        "intent_id": "intent_review"
      }
    },
    "workflow_convention_inference": {
      "id": "workflow_convention_inference",
      "label": "convention_inference_workflow",
      "entity_type": "TCGWorkflowPattern",
      "description": "Convention-inference seed: glob for existing artifacts, read one example, infer location and style, write. First-class product feature per",
      "properties": {
        "tool_sequence": [
          "tool_graq_glob",
          "tool_graq_read",
          "tool_graq_write"
        ],
        "support_count": 10,
        "graduated": true,
        "intent_id": "intent_write_new_artifact"
      }
    },
    "lesson_sdk_hf_01": {
      "id": "lesson_sdk_hf_01",
      "label": "SDK-HF-01 DAG missing graq_generate",
      "entity_type": "TCGLesson",
      "description": "The extension orchestrator built a DAG without graq_generate for codegen intent. ChatAgentLoop v4 TCG activation is the structural fix",
      "properties": {
        "severity": "HIGH",
        "hit_count": 1
      }
    },
    "lesson_cg_dif_01": {
      "id": "lesson_cg_dif_01",
      "label": "graq_edit hub-file insertion failure pattern",
      "entity_type": "TCGLesson",
      "description": "graq_edit fails on hub files with multiple lookalike methods. Pivot to graq_apply",
      "properties": {
        "severity": "HIGH",
        "hit_count": 3
      }
    },
    "lesson_ot_060": {
      "id": "lesson_ot_060",
      "label": "Neo4j disable-env-var gate",
      "entity_type": "TCGLesson",
      "description": "When NEO4J_DISABLED=true, Graqle.from_neo4j/to_neo4j raise before dialing bolt://",
      "properties": {
        "severity": "MEDIUM",
        "hit_count": 132
      }
    },
    "lesson_ot_062": {
      "id": "lesson_ot_062",
      "label": "Per-instance session gate pattern",
      "entity_type": "TCGLesson",
      "description": "Each KogniDevServer instance is its own MCP session container. Per-instance bypass attrs are session-scoped",
      "properties": {
        "severity": "MEDIUM",
        "hit_count": 130
      }
    },
    "lesson_ot_061": {
      "id": "lesson_ot_061",
      "label": "Credential access dedupe pattern",
      "entity_type": "TCGLesson",
      "description": "Module-level sentinel for boto3 AccessDenied dedupe to avoid log flooding",
      "properties": {
        "severity": "MEDIUM",
        "hit_count": 130
      }
    },
    "lesson_cg_reason_02": {
      "id": "lesson_cg_reason_02",
      "label": "Backend pickling crash pattern",
      "entity_type": "TCGLesson",
      "description": "Backend instances crashed with _thread.RLock pickle error on deepcopy. Fixed via __getstate__/__setstate__ drop-transients pattern",
      "properties": {
        "severity": "CRITICAL",
        "hit_count": 45
      }
    },
    "lesson_sdk_hf_02": {
      "id": "lesson_sdk_hf_02",
      "label": "SDK-HF-02 synthesis truncation",
      "entity_type": "TCGLesson",
      "description": "Synthesis hit stop_reason=max_tokens and returned truncated text. Fixed via generate_with_continuation helper",
      "properties": {
        "severity": "HIGH",
        "hit_count": 34
      }
    },
    "lesson_cg_reason_01": {
      "id": "lesson_cg_reason_01",
      "label": "Batch reasoning fallback pattern",
      "entity_type": "TCGLesson",
      "description": "areason_batch error branch crashed constructing ReasoningResult with node_count. Fixed via _make_error_result helper",
      "properties": {
        "severity": "HIGH",
        "hit_count": 9
      }
    },
    "lesson_tb_f1_isolation": {
      "id": "lesson_tb_f1_isolation",
      "label": "Source-level isolation test pattern",
      "entity_type": "TCGLesson",
      "description": "Isolation tests must scan source imports, not runtime sys.modules, because parent __init__ eagerly loads submodules",
      "properties": {
        "severity": "MEDIUM",
        "hit_count": 1
      }
    },
    "lesson_reason_cold": {
      "id": "lesson_reason_cold",
      "label": "graq_reason cold-call anti-pattern",
      "entity_type": "TCGLesson",
      "description": "Calling graq_reason without prior graq_context/graq_inspect yields low-confidence cold answers",
      "properties": {
        "severity": "MEDIUM",
        "hit_count": 12
      }
    },
    "lesson_pytest_full": {
      "id": "lesson_pytest_full",
      "label": "pytest tests/ crashes on Windows",
      "entity_type": "TCGLesson",
      "description": "Full pytest without a focused path can overload parallel test workers on some environments. Always use focused paths.",
      "properties": {
        "severity": "HIGH",
        "hit_count": 8
      }
    },
    "lesson_graq_apply_hub": {
      "id": "lesson_graq_apply_hub",
      "label": "graq_apply on hub files",
      "entity_type": "TCGLesson",
      "description": "Hub files (impact_radius > 20 or > 1500 lines) must use graq_apply, not graq_edit",
      "properties": {
        "severity": "HIGH",
        "hit_count": 5
      }
    },
    "lesson_dry_run_first": {
      "id": "lesson_dry_run_first",
      "label": "always dry_run=True first",
      "entity_type": "TCGLesson",
      "description": "Every governed write tool defaults to dry_run=True. Explicit dry_run=False only after validation",
      "properties": {
        "severity": "MEDIUM",
        "hit_count": 20
      }
    },
    "lesson_convention_inf": {
      "id": "lesson_convention_inf",
      "label": "convention inference first, no asking",
      "entity_type": "TCGLesson",
      "description": "Never ask where files go or what the next sequence number is. Glob for existing artifacts, read one example, infer",
      "properties": {
        "severity": "HIGH",
        "hit_count": 3
      }
    },
    "lesson_patent_scrub": {
      "id": "lesson_patent_scrub",
      "label": "patent scan blocks credentials literals",
      "entity_type": "TCGLesson",
      "description": "Patent scan rejects literal 'api_key', 'secret', 'token' in docstrings. Use 'credentials env-var name' or 'placeholder'",
      "properties": {
        "severity": "MEDIUM",
        "hit_count": 4
      }
    },
    "lesson_governance_tier": {
      "id": "lesson_governance_tier",
      "label": "governance tier upfront disclosure",
      "entity_type": "TCGLesson",
      "description": "Governance tiers live on TCG tool nodes as attributes. Pre-disclosed upfront. Never surprise-block mid-flow",
      "properties": {
        "severity": "MEDIUM",
        "hit_count": 1
      }
    },
    "lesson_probation": {
      "id": "lesson_probation",
      "label": "workflow probation before graduation",
      "entity_type": "TCGLesson",
      "description": "Candidate workflow patterns stay in probation until holdout validation. Prevents pollution from coincidental repetition",
      "properties": {
        "severity": "MEDIUM",
        "hit_count": 1
      }
    },
    "lesson_destructive": {
      "id": "lesson_destructive",
      "label": "destructive-edge safety filter",
      "entity_type": "TCGLesson",
      "description": "Predicted missing edges must pass a non-destructive allowlist. Never suggest graq_bash -> graq_delete_all even if support is high",
      "properties": {
        "severity": "CRITICAL",
        "hit_count": 1
      }
    },
    "lesson_weight_clamp": {
      "id": "lesson_weight_clamp",
      "label": "edge weight clamp [0.0, 10.0]",
      "entity_type": "TCGLesson",
      "description": "Every reinforcement path must clamp the new weight to [0.0, 10.0] to prevent runaway reinforcement",
      "properties": {
        "severity": "LOW",
        "hit_count": 1
      }
    },
    "lesson_atomic_save": {
      "id": "lesson_atomic_save",
      "label": "TCG atomic save with .bak rollback",
      "entity_type": "TCGLesson",
      "description": "TCG persistence: write temp -> fsync -> rotate current to .bak -> os.replace(temp, target) -> cleanup. Rollback on any failure",
      "properties": {
        "severity": "HIGH",
        "hit_count": 1
      }
    },
    "tool_graq_gov_gate": {
      "id": "tool_graq_gov_gate",
      "label": "graq_gov_gate",
      "entity_type": "TCGTool",
      "description": "Governance gate check — runs governance constraint verification before a change",
      "properties": {
        "governance_tier": "GREEN",
        "side_effect": "read",
        "category": "governance",
        "latency_tier": "medium",
        "safe_for_prediction": true
      }
    },
    "tool_graq_safety_check": {
      "id": "tool_graq_safety_check",
      "label": "graq_safety_check",
      "entity_type": "TCGTool",
      "description": "Fast safety check for a proposed action against project safety boundaries",
      "properties": {
        "governance_tier": "GREEN",
        "side_effect": "read",
        "category": "governance",
        "latency_tier": "fast",
        "safe_for_prediction": true
      }
    },
    "tool_graq_audit": {
      "id": "tool_graq_audit",
      "label": "graq_audit",
      "entity_type": "TCGTool",
      "description": "Read-only audit trail inspection. Used by R18 GETC trace capture flow",
      "properties": {
        "governance_tier": "GREEN",
        "side_effect": "read",
        "category": "governance",
        "latency_tier": "medium",
        "safe_for_prediction": true
      }
    },
    "tool_graq_runtime": {
      "id": "tool_graq_runtime",
      "label": "graq_runtime",
      "entity_type": "TCGTool",
      "description": "Runtime introspection of current governance state. Used by R18 GETC",
      "properties": {
        "governance_tier": "GREEN",
        "side_effect": "read",
        "category": "governance",
        "latency_tier": "fast",
        "safe_for_prediction": true
      }
    },
    "tool_graq_phantom_browse": {
      "id": "tool_graq_phantom_browse",
      "label": "graq_phantom_browse",
      "entity_type": "TCGTool",
      "description": "Browse a URL with a headless browser session",
      "properties": {
        "governance_tier": "YELLOW",
        "side_effect": "net",
        "category": "phantom",
        "latency_tier": "slow",
        "safe_for_prediction": true
      }
    },
    "tool_graq_phantom_click": {
      "id": "tool_graq_phantom_click",
      "label": "graq_phantom_click",
      "entity_type": "TCGTool",
      "description": "Click an element in an active phantom session",
      "properties": {
        "governance_tier": "YELLOW",
        "side_effect": "net",
        "category": "phantom",
        "latency_tier": "medium",
        "safe_for_prediction": true
      }
    },
    "tool_graq_phantom_type": {
      "id": "tool_graq_phantom_type",
      "label": "graq_phantom_type",
      "entity_type": "TCGTool",
      "description": "Type into a field in an active phantom session",
      "properties": {
        "governance_tier": "YELLOW",
        "side_effect": "net",
        "category": "phantom",
        "latency_tier": "medium",
        "safe_for_prediction": true
      }
    },
    "tool_graq_phantom_screenshot": {
      "id": "tool_graq_phantom_screenshot",
      "label": "graq_phantom_screenshot",
      "entity_type": "TCGTool",
      "description": "Capture a screenshot of the current phantom page. JS execution via remote page makes this a governed operation",
      "properties": {
        "governance_tier": "YELLOW",
        "side_effect": "net",
        "category": "phantom",
        "latency_tier": "medium",
        "safe_for_prediction": true
      }
    },
    "tool_graq_phantom_audit": {
      "id": "tool_graq_phantom_audit",
      "label": "graq_phantom_audit",
      "entity_type": "TCGTool",
      "description": "Run an automated audit (accessibility, perf, etc.) against the page",
      "properties": {
        "governance_tier": "GREEN",
        "side_effect": "read",
        "category": "phantom",
        "latency_tier": "slow",
        "safe_for_prediction": true
      }
    },
    "tool_graq_phantom_session": {
      "id": "tool_graq_phantom_session",
      "label": "graq_phantom_session",
      "entity_type": "TCGTool",
      "description": "Manage a phantom browser session (create, resume, close)",
      "properties": {
        "governance_tier": "YELLOW",
        "side_effect": "net",
        "category": "phantom",
        "latency_tier": "fast",
        "safe_for_prediction": true
      }
    },
    "tool_graq_phantom_discover": {
      "id": "tool_graq_phantom_discover",
      "label": "graq_phantom_discover",
      "entity_type": "TCGTool",
      "description": "Crawl-discover pages reachable from a URL",
      "properties": {
        "governance_tier": "YELLOW",
        "side_effect": "net",
        "category": "phantom",
        "latency_tier": "slow",
        "safe_for_prediction": true
      }
    },
    "tool_graq_phantom_flow": {
      "id": "tool_graq_phantom_flow",
      "label": "graq_phantom_flow",
      "entity_type": "TCGTool",
      "description": "Execute a scripted multi-step browser flow",
      "properties": {
        "governance_tier": "YELLOW",
        "side_effect": "net",
        "category": "phantom",
        "latency_tier": "slow",
        "safe_for_prediction": true
      }
    },
    "tool_graq_scorch_audit": {
      "id": "tool_graq_scorch_audit",
      "label": "graq_scorch_audit",
      "entity_type": "TCGTool",
      "description": "Full SCORCH UX audit across a target URL or build",
      "properties": {
        "governance_tier": "GREEN",
        "side_effect": "read",
        "category": "scorch",
        "latency_tier": "slow",
        "safe_for_prediction": true
      }
    },
    "tool_graq_scorch_report": {
      "id": "tool_graq_scorch_report",
      "label": "graq_scorch_report",
      "entity_type": "TCGTool",
      "description": "Generate a SCORCH audit report from a prior run",
      "properties": {
        "governance_tier": "GREEN",
        "side_effect": "read",
        "category": "scorch",
        "latency_tier": "medium",
        "safe_for_prediction": true
      }
    },
    "tool_graq_scorch_a11y": {
      "id": "tool_graq_scorch_a11y",
      "label": "graq_scorch_a11y",
      "entity_type": "TCGTool",
      "description": "Accessibility-only SCORCH audit (WCAG)",
      "properties": {
        "governance_tier": "GREEN",
        "side_effect": "read",
        "category": "scorch",
        "latency_tier": "slow",
        "safe_for_prediction": true
      }
    },
    "tool_graq_scorch_perf": {
      "id": "tool_graq_scorch_perf",
      "label": "graq_scorch_perf",
      "entity_type": "TCGTool",
      "description": "Performance-only SCORCH audit (Core Web Vitals)",
      "properties": {
        "governance_tier": "GREEN",
        "side_effect": "read",
        "category": "scorch",
        "latency_tier": "slow",
        "safe_for_prediction": true
      }
    },
    "tool_graq_scorch_seo": {
      "id": "tool_graq_scorch_seo",
      "label": "graq_scorch_seo",
      "entity_type": "TCGTool",
      "description": "SEO-only SCORCH audit",
      "properties": {
        "governance_tier": "GREEN",
        "side_effect": "read",
        "category": "scorch",
        "latency_tier": "slow",
        "safe_for_prediction": true
      }
    },
    "tool_graq_scorch_mobile": {
      "id": "tool_graq_scorch_mobile",
      "label": "graq_scorch_mobile",
      "entity_type": "TCGTool",
      "description": "Mobile-responsive SCORCH audit",
      "properties": {
        "governance_tier": "GREEN",
        "side_effect": "read",
        "category": "scorch",
        "latency_tier": "slow",
        "safe_for_prediction": true
      }
    },
    "tool_graq_scorch_i18n": {
      "id": "tool_graq_scorch_i18n",
      "label": "graq_scorch_i18n",
      "entity_type": "TCGTool",
      "description": "i18n / RTL / encoding SCORCH audit",
      "properties": {
        "governance_tier": "GREEN",
        "side_effect": "read",
        "category": "scorch",
        "latency_tier": "slow",
        "safe_for_prediction": true
      }
    },
    "tool_graq_scorch_security": {
      "id": "tool_graq_scorch_security",
      "label": "graq_scorch_security",
      "entity_type": "TCGTool",
      "description": "Security headers + CSP SCORCH audit",
      "properties": {
        "governance_tier": "GREEN",
        "side_effect": "read",
        "category": "scorch",
        "latency_tier": "slow",
        "safe_for_prediction": true
      }
    },
    "tool_graq_scorch_conversion": {
      "id": "tool_graq_scorch_conversion",
      "label": "graq_scorch_conversion",
      "entity_type": "TCGTool",
      "description": "Conversion-funnel SCORCH audit",
      "properties": {
        "governance_tier": "GREEN",
        "side_effect": "read",
        "category": "scorch",
        "latency_tier": "slow",
        "safe_for_prediction": true
      }
    },
    "tool_graq_scorch_brand": {
      "id": "tool_graq_scorch_brand",
      "label": "graq_scorch_brand",
      "entity_type": "TCGTool",
      "description": "Brand-consistency SCORCH audit",
      "properties": {
        "governance_tier": "GREEN",
        "side_effect": "read",
        "category": "scorch",
        "latency_tier": "slow",
        "safe_for_prediction": true
      }
    },
    "tool_graq_scorch_auth_flow": {
      "id": "tool_graq_scorch_auth_flow",
      "label": "graq_scorch_auth_flow",
      "entity_type": "TCGTool",
      "description": "Auth-flow SCORCH audit",
      "properties": {
        "governance_tier": "GREEN",
        "side_effect": "read",
        "category": "scorch",
        "latency_tier": "slow",
        "safe_for_prediction": true
      }
    },
    "tool_graq_scorch_behavioral": {
      "id": "tool_graq_scorch_behavioral",
      "label": "graq_scorch_behavioral",
      "entity_type": "TCGTool",
      "description": "Behavioral / user-interaction SCORCH audit",
      "properties": {
        "governance_tier": "GREEN",
        "side_effect": "read",
        "category": "scorch",
        "latency_tier": "slow",
        "safe_for_prediction": true
      }
    },
    "tool_graq_scorch_diff": {
      "id": "tool_graq_scorch_diff",
      "label": "graq_scorch_diff",
      "entity_type": "TCGTool",
      "description": "Diff SCORCH audit results between two runs",
      "properties": {
        "governance_tier": "GREEN",
        "side_effect": "read",
        "category": "scorch",
        "latency_tier": "medium",
        "safe_for_prediction": true
      }
    },
    "tool_graq_lifecycle": {
      "id": "tool_graq_lifecycle",
      "label": "graq_lifecycle",
      "entity_type": "TCGTool",
      "description": "Session lifecycle hooks (session_start / fix_complete)",
      "properties": {
        "governance_tier": "GREEN",
        "side_effect": "read",
        "category": "lifecycle",
        "latency_tier": "fast",
        "safe_for_prediction": true
      }
    },
    "tool_graq_drace": {
      "id": "tool_graq_drace",
      "label": "graq_drace",
      "entity_type": "TCGTool",
      "description": "DRACE reasoning-chain tracer",
      "properties": {
        "governance_tier": "GREEN",
        "side_effect": "read",
        "category": "lifecycle",
        "latency_tier": "medium",
        "safe_for_prediction": true
      }
    },
    "tool_graq_workflow": {
      "id": "tool_graq_workflow",
      "label": "graq_workflow",
      "entity_type": "TCGTool",
      "description": "Run a pre-defined ordered tool workflow (bug_fix / scaffold / governed_refactor / review_and_fix)",
      "properties": {
        "governance_tier": "GREEN",
        "side_effect": "read",
        "category": "workflow",
        "latency_tier": "fast",
        "safe_for_prediction": true
      }
    },
    "tool_graq_auto": {
      "id": "tool_graq_auto",
      "label": "graq_auto",
      "entity_type": "TCGTool",
      "description": "Autonomous multi-step agent run — classify, plan, execute, learn",
      "properties": {
        "governance_tier": "YELLOW",
        "side_effect": "compute",
        "category": "workflow",
        "latency_tier": "slow",
        "safe_for_prediction": true
      }
    },
    "tool_graq_route": {
      "id": "tool_graq_route",
      "label": "graq_route",
      "entity_type": "TCGTool",
      "description": "Classify a user query and pick the cheapest viable tool",
      "properties": {
        "governance_tier": "GREEN",
        "side_effect": "read",
        "category": "workflow",
        "latency_tier": "fast",
        "safe_for_prediction": true
      }
    },
    "tool_graq_correct": {
      "id": "tool_graq_correct",
      "label": "graq_correct",
      "entity_type": "TCGTool",
      "description": "Governed self-correction loop over a prior result",
      "properties": {
        "governance_tier": "YELLOW",
        "side_effect": "compute",
        "category": "workflow",
        "latency_tier": "medium",
        "safe_for_prediction": true
      }
    },
    "tool_graq_profile": {
      "id": "tool_graq_profile",
      "label": "graq_profile",
      "entity_type": "TCGTool",
      "description": "Read/update the project profile used by reformulator",
      "properties": {
        "governance_tier": "GREEN",
        "side_effect": "read",
        "category": "profile",
        "latency_tier": "medium",
        "safe_for_prediction": true
      }
    },
    "tool_graq_web_search": {
      "id": "tool_graq_web_search",
      "label": "graq_web_search",
      "entity_type": "TCGTool",
      "description": "Web search — external lookups for context enrichment",
      "properties": {
        "governance_tier": "YELLOW",
        "side_effect": "net",
        "category": "search",
        "latency_tier": "medium",
        "safe_for_prediction": true
      }
    },
    "tool_graq_plan": {
      "id": "tool_graq_plan",
      "label": "graq_plan",
      "entity_type": "TCGTool",
      "description": "Plan-as-graph decomposition",
      "properties": {
        "governance_tier": "GREEN",
        "side_effect": "compute",
        "category": "plan",
        "latency_tier": "medium",
        "safe_for_prediction": true
      }
    },
    "tool_graq_github_pr": {
      "id": "tool_graq_github_pr",
      "label": "graq_github_pr",
      "entity_type": "TCGTool",
      "description": "Read or create a GitHub pull request",
      "properties": {
        "governance_tier": "YELLOW",
        "side_effect": "net",
        "category": "git",
        "latency_tier": "medium",
        "safe_for_prediction": true
      }
    },
    "tool_graq_github_diff": {
      "id": "tool_graq_github_diff",
      "label": "graq_github_diff",
      "entity_type": "TCGTool",
      "description": "Read a GitHub pull request diff",
      "properties": {
        "governance_tier": "GREEN",
        "side_effect": "read",
        "category": "git",
        "latency_tier": "medium",
        "safe_for_prediction": true
      }
    },
    "tool_graq_todo": {
      "id": "tool_graq_todo",
      "label": "graq_todo",
      "entity_type": "TCGTool",
      "description": "Governed per-session todo list",
      "properties": {
        "governance_tier": "GREEN",
        "side_effect": "read",
        "category": "session",
        "latency_tier": "fast",
        "safe_for_prediction": true
      }
    },
    "intent_visual_audit": {
      "id": "intent_visual_audit",
      "label": "visual_audit",
      "entity_type": "TCGIntent",
      "description": "User wants a UI / UX / accessibility / SEO visual audit on a running page",
      "properties": {
        "keywords": [
          "audit ui",
          "visual audit",
          "a11y",
          "accessibility",
          "seo audit",
          "performance audit",
          "mobile audit",
          "i18n audit",
          "brand audit",
          "scorch",
          "screenshot"
        ],
        "preferred_sequence": [
          "tool_graq_phantom_session",
          "tool_graq_phantom_browse",
          "tool_graq_scorch_audit",
          "tool_graq_scorch_report"
        ]
      }
    },
    "intent_browser_automation": {
      "id": "intent_browser_automation",
      "label": "browser_automation",
      "entity_type": "TCGIntent",
      "description": "User wants to drive a browser session (click, type, navigate, discover)",
      "properties": {
        "keywords": [
          "click",
          "type in",
          "fill form",
          "navigate to",
          "open url",
          "browser flow",
          "phantom",
          "scrape",
          "crawl",
          "screenshot"
        ],
        "preferred_sequence": [
          "tool_graq_phantom_session",
          "tool_graq_phantom_browse",
          "tool_graq_phantom_click",
          "tool_graq_phantom_type"
        ]
      }
    },
    "intent_production_deploy_check": {
      "id": "intent_production_deploy_check",
      "label": "production_deploy_check",
      "entity_type": "TCGIntent",
      "description": "User wants to validate a production deployment via web-facing checks + audit trail",
      "properties": {
        "keywords": [
          "production",
          "deploy check",
          "smoke test",
          "post-deploy",
          "canary",
          "rollout"
        ],
        "preferred_sequence": [
          "tool_graq_phantom_browse",
          "tool_graq_scorch_audit",
          "tool_graq_audit",
          "tool_graq_runtime"
        ]
      }
    },
    "intent_dependency_management": {
      "id": "intent_dependency_management",
      "label": "dependency_management",
      "entity_type": "TCGIntent",
      "description": "User wants to vendor, ingest external docs, or reload the graph",
      "properties": {
        "keywords": [
          "vendor",
          "ingest",
          "reload",
          "import dependency",
          "external doc"
        ],
        "preferred_sequence": [
          "tool_graq_vendor",
          "tool_graq_ingest",
          "tool_graq_reload"
        ]
      }
    },
    "intent_autonomous_task": {
      "id": "intent_autonomous_task",
      "label": "autonomous_task",
      "entity_type": "TCGIntent",
      "description": "User wants an autonomous multi-step agent run with planning, routing, and correction",
      "properties": {
        "keywords": [
          "autonomous",
          "auto mode",
          "full auto",
          "self-correct",
          "plan and run",
          "end-to-end"
        ],
        "preferred_sequence": [
          "tool_graq_plan",
          "tool_graq_route",
          "tool_graq_auto",
          "tool_graq_correct",
          "tool_graq_workflow"
        ]
      }
    },
    "intent_knowledge_lookup": {
      "id": "intent_knowledge_lookup",
      "label": "knowledge_lookup",
      "entity_type": "TCGIntent",
      "description": "User wants to retrieve lessons, knowledge, recent activity, or profile info",
      "properties": {
        "keywords": [
          "lessons",
          "past mistake",
          "profile",
          "activity log",
          "history",
          "web search",
          "look up"
        ],
        "preferred_sequence": [
          "tool_graq_lessons",
          "tool_graq_profile",
          "tool_graq_web_search",
          "tool_graq_git_log"
        ]
      }
    },
    "intent_review_pr": {
      "id": "intent_review_pr",
      "label": "review_pr",
      "entity_type": "TCGIntent",
      "description": "User wants to review a GitHub PR diff",
      "properties": {
        "keywords": [
          "github pr",
          "pr review",
          "pull request",
          "github diff"
        ],
        "preferred_sequence": [
          "tool_graq_github_pr",
          "tool_graq_github_diff",
          "tool_graq_review",
          "tool_graq_reason_batch"
        ]
      }
    },
    "intent_trace_reasoning": {
      "id": "intent_trace_reasoning",
      "label": "trace_reasoning",
      "entity_type": "TCGIntent",
      "description": "User wants to trace a prior reasoning chain or run a batch of parallel reasoning queries",
      "properties": {
        "keywords": [
          "trace",
          "drace",
          "reasoning chain",
          "batch reason",
          "parallel query",
          "predict"
        ],
        "preferred_sequence": [
          "tool_graq_drace",
          "tool_graq_reason_batch",
          "tool_graq_predict",
          "tool_graq_lifecycle"
        ]
      }
    },
    "workflow_visual_audit": {
      "id": "workflow_visual_audit",
      "label": "visual_audit_workflow",
      "entity_type": "TCGWorkflowPattern",
      "description": "Visual audit pipeline — browse -> audit -> report",
      "properties": {
        "tool_sequence": [
          "tool_graq_phantom_session",
          "tool_graq_phantom_browse",
          "tool_graq_scorch_audit",
          "tool_graq_scorch_report"
        ],
        "support_count": 10,
        "graduated": true,
        "intent_id": "intent_visual_audit"
      }
    },
    "workflow_autonomous_task": {
      "id": "workflow_autonomous_task",
      "label": "autonomous_task_workflow",
      "entity_type": "TCGWorkflowPattern",
      "description": "Plan -> route -> auto -> correct full autonomous loop",
      "properties": {
        "tool_sequence": [
          "tool_graq_plan",
          "tool_graq_route",
          "tool_graq_auto",
          "tool_graq_correct"
        ],
        "support_count": 10,
        "graduated": true,
        "intent_id": "intent_autonomous_task"
      }
    },
    "workflow_review_pr": {
      "id": "workflow_review_pr",
      "label": "review_pr_workflow",
      "entity_type": "TCGWorkflowPattern",
      "description": "Fetch PR -> diff -> review -> batch reason",
      "properties": {
        "tool_sequence": [
          "tool_graq_github_pr",
          "tool_graq_github_diff",
          "tool_graq_review",
          "tool_graq_reason_batch"
        ],
        "support_count": 10,
        "graduated": true,
        "intent_id": "intent_review_pr"
      }
    }
  },
  "edges": [
    {
      "id": "e_codegen_generate",
      "source_id": "intent_codegen",
      "target_id": "tool_graq_generate",
      "relationship": "MATCHES_INTENT",
      "weight": 3.0
    },
    {
      "id": "e_codegen_reason",
      "source_id": "intent_codegen",
      "target_id": "tool_graq_reason",
      "relationship": "MATCHES_INTENT",
      "weight": 2.0
    },
    {
      "id": "e_codegen_context",
      "source_id": "intent_codegen",
      "target_id": "tool_graq_context",
      "relationship": "MATCHES_INTENT",
      "weight": 2.0
    },
    {
      "id": "e_codegen_scaffold",
      "source_id": "intent_codegen",
      "target_id": "tool_graq_scaffold",
      "relationship": "MATCHES_INTENT",
      "weight": 1.5
    },
    {
      "id": "e_codegen_preflight",
      "source_id": "intent_codegen",
      "target_id": "tool_graq_preflight",
      "relationship": "MATCHES_INTENT",
      "weight": 1.0
    },
    {
      "id": "e_bugfix_grep",
      "source_id": "intent_bug_fix",
      "target_id": "tool_graq_grep",
      "relationship": "MATCHES_INTENT",
      "weight": 3.0
    },
    {
      "id": "e_bugfix_read",
      "source_id": "intent_bug_fix",
      "target_id": "tool_graq_read",
      "relationship": "MATCHES_INTENT",
      "weight": 2.5
    },
    {
      "id": "e_bugfix_debug",
      "source_id": "intent_bug_fix",
      "target_id": "tool_graq_debug",
      "relationship": "MATCHES_INTENT",
      "weight": 2.5
    },
    {
      "id": "e_bugfix_generate",
      "source_id": "intent_bug_fix",
      "target_id": "tool_graq_generate",
      "relationship": "MATCHES_INTENT",
      "weight": 2.0
    },
    {
      "id": "e_bugfix_test",
      "source_id": "intent_bug_fix",
      "target_id": "tool_graq_test",
      "relationship": "MATCHES_INTENT",
      "weight": 1.5
    },
    {
      "id": "e_refactor_impact",
      "source_id": "intent_refactor",
      "target_id": "tool_graq_impact",
      "relationship": "MATCHES_INTENT",
      "weight": 3.0
    },
    {
      "id": "e_refactor_preflight",
      "source_id": "intent_refactor",
      "target_id": "tool_graq_preflight",
      "relationship": "MATCHES_INTENT",
      "weight": 2.5
    },
    {
      "id": "e_refactor_generate",
      "source_id": "intent_refactor",
      "target_id": "tool_graq_generate",
      "relationship": "MATCHES_INTENT",
      "weight": 2.0
    },
    {
      "id": "e_refactor_apply",
      "source_id": "intent_refactor",
      "target_id": "tool_graq_apply",
      "relationship": "MATCHES_INTENT",
      "weight": 1.5
    },
    {
      "id": "e_audit_inspect",
      "source_id": "intent_audit",
      "target_id": "tool_graq_inspect",
      "relationship": "MATCHES_INTENT",
      "weight": 3.0
    },
    {
      "id": "e_audit_context",
      "source_id": "intent_audit",
      "target_id": "tool_graq_context",
      "relationship": "MATCHES_INTENT",
      "weight": 2.5
    },
    {
      "id": "e_audit_impact",
      "source_id": "intent_audit",
      "target_id": "tool_graq_impact",
      "relationship": "MATCHES_INTENT",
      "weight": 2.0
    },
    {
      "id": "e_review_read",
      "source_id": "intent_review",
      "target_id": "tool_graq_read",
      "relationship": "MATCHES_INTENT",
      "weight": 2.5
    },
    {
      "id": "e_review_review",
      "source_id": "intent_review",
      "target_id": "tool_graq_review",
      "relationship": "MATCHES_INTENT",
      "weight": 3.0
    },
    {
      "id": "e_explain_context",
      "source_id": "intent_explain",
      "target_id": "tool_graq_context",
      "relationship": "MATCHES_INTENT",
      "weight": 3.0
    },
    {
      "id": "e_explain_reason",
      "source_id": "intent_explain",
      "target_id": "tool_graq_reason",
      "relationship": "MATCHES_INTENT",
      "weight": 2.5
    },
    {
      "id": "e_search_glob",
      "source_id": "intent_search",
      "target_id": "tool_graq_glob",
      "relationship": "MATCHES_INTENT",
      "weight": 3.0
    },
    {
      "id": "e_search_grep",
      "source_id": "intent_search",
      "target_id": "tool_graq_grep",
      "relationship": "MATCHES_INTENT",
      "weight": 3.0
    },
    {
      "id": "e_test_read",
      "source_id": "intent_test",
      "target_id": "tool_graq_read",
      "relationship": "MATCHES_INTENT",
      "weight": 2.0
    },
    {
      "id": "e_test_generate",
      "source_id": "intent_test",
      "target_id": "tool_graq_generate",
      "relationship": "MATCHES_INTENT",
      "weight": 2.5
    },
    {
      "id": "e_test_test",
      "source_id": "intent_test",
      "target_id": "tool_graq_test",
      "relationship": "MATCHES_INTENT",
      "weight": 3.0
    },
    {
      "id": "e_wna_glob",
      "source_id": "intent_write_new_artifact",
      "target_id": "tool_graq_glob",
      "relationship": "MATCHES_INTENT",
      "weight": 3.0
    },
    {
      "id": "e_wna_read",
      "source_id": "intent_write_new_artifact",
      "target_id": "tool_graq_read",
      "relationship": "MATCHES_INTENT",
      "weight": 2.5
    },
    {
      "id": "e_wna_write",
      "source_id": "intent_write_new_artifact",
      "target_id": "tool_graq_write",
      "relationship": "MATCHES_INTENT",
      "weight": 3.0
    },
    {
      "id": "e_gitst_status",
      "source_id": "intent_git_status",
      "target_id": "tool_graq_git_status",
      "relationship": "MATCHES_INTENT",
      "weight": 3.0
    },
    {
      "id": "e_gitst_diff",
      "source_id": "intent_git_status",
      "target_id": "tool_graq_git_diff",
      "relationship": "MATCHES_INTENT",
      "weight": 2.5
    },
    {
      "id": "e_commit_status",
      "source_id": "intent_commit",
      "target_id": "tool_graq_git_status",
      "relationship": "MATCHES_INTENT",
      "weight": 2.0
    },
    {
      "id": "e_commit_diff",
      "source_id": "intent_commit",
      "target_id": "tool_graq_git_diff",
      "relationship": "MATCHES_INTENT",
      "weight": 2.0
    },
    {
      "id": "e_commit_commit",
      "source_id": "intent_commit",
      "target_id": "tool_graq_git_commit",
      "relationship": "MATCHES_INTENT",
      "weight": 3.0
    },
    {
      "id": "e_gref_branch",
      "source_id": "intent_governed_refactor",
      "target_id": "tool_graq_git_branch",
      "relationship": "MATCHES_INTENT",
      "weight": 2.0
    },
    {
      "id": "e_gref_impact",
      "source_id": "intent_governed_refactor",
      "target_id": "tool_graq_impact",
      "relationship": "MATCHES_INTENT",
      "weight": 2.5
    },
    {
      "id": "e_gref_preflight",
      "source_id": "intent_governed_refactor",
      "target_id": "tool_graq_preflight",
      "relationship": "MATCHES_INTENT",
      "weight": 2.5
    },
    {
      "id": "e_gref_generate",
      "source_id": "intent_governed_refactor",
      "target_id": "tool_graq_generate",
      "relationship": "MATCHES_INTENT",
      "weight": 2.5
    },
    {
      "id": "e_gref_gate",
      "source_id": "intent_governed_refactor",
      "target_id": "tool_graq_gate",
      "relationship": "MATCHES_INTENT",
      "weight": 2.0
    },
    {
      "id": "e_seq_read_after_grep",
      "source_id": "tool_graq_read",
      "target_id": "tool_graq_grep",
      "relationship": "USED_AFTER",
      "weight": 3.0
    },
    {
      "id": "e_seq_debug_after_read",
      "source_id": "tool_graq_debug",
      "target_id": "tool_graq_read",
      "relationship": "USED_AFTER",
      "weight": 2.5
    },
    {
      "id": "e_seq_gen_after_debug",
      "source_id": "tool_graq_generate",
      "target_id": "tool_graq_debug",
      "relationship": "USED_AFTER",
      "weight": 2.5
    },
    {
      "id": "e_seq_gen_after_reason",
      "source_id": "tool_graq_generate",
      "target_id": "tool_graq_reason",
      "relationship": "USED_AFTER",
      "weight": 3.5
    },
    {
      "id": "e_seq_gen_after_context",
      "source_id": "tool_graq_generate",
      "target_id": "tool_graq_context",
      "relationship": "USED_AFTER",
      "weight": 2.5
    },
    {
      "id": "e_seq_reason_after_ctx",
      "source_id": "tool_graq_reason",
      "target_id": "tool_graq_context",
      "relationship": "USED_AFTER",
      "weight": 4.0
    },
    {
      "id": "e_seq_context_after_insp",
      "source_id": "tool_graq_context",
      "target_id": "tool_graq_inspect",
      "relationship": "USED_AFTER",
      "weight": 2.0
    },
    {
      "id": "e_seq_edit_after_gen",
      "source_id": "tool_graq_edit",
      "target_id": "tool_graq_generate",
      "relationship": "USED_AFTER",
      "weight": 2.0
    },
    {
      "id": "e_seq_write_after_gen",
      "source_id": "tool_graq_write",
      "target_id": "tool_graq_generate",
      "relationship": "USED_AFTER",
      "weight": 2.0
    },
    {
      "id": "e_seq_apply_after_gen",
      "source_id": "tool_graq_apply",
      "target_id": "tool_graq_generate",
      "relationship": "USED_AFTER",
      "weight": 2.0
    },
    {
      "id": "e_seq_test_after_edit",
      "source_id": "tool_graq_test",
      "target_id": "tool_graq_edit",
      "relationship": "USED_AFTER",
      "weight": 2.5
    },
    {
      "id": "e_seq_test_after_write",
      "source_id": "tool_graq_test",
      "target_id": "tool_graq_write",
      "relationship": "USED_AFTER",
      "weight": 2.5
    },
    {
      "id": "e_seq_test_after_apply",
      "source_id": "tool_graq_test",
      "target_id": "tool_graq_apply",
      "relationship": "USED_AFTER",
      "weight": 2.5
    },
    {
      "id": "e_seq_commit_after_test",
      "source_id": "tool_graq_git_commit",
      "target_id": "tool_graq_test",
      "relationship": "USED_AFTER",
      "weight": 3.0
    },
    {
      "id": "e_seq_commit_after_diff",
      "source_id": "tool_graq_git_commit",
      "target_id": "tool_graq_git_diff",
      "relationship": "USED_AFTER",
      "weight": 2.5
    },
    {
      "id": "e_seq_learn_after_commit",
      "source_id": "tool_graq_learn",
      "target_id": "tool_graq_git_commit",
      "relationship": "USED_AFTER",
      "weight": 2.0
    },
    {
      "id": "e_seq_read_after_glob",
      "source_id": "tool_graq_read",
      "target_id": "tool_graq_glob",
      "relationship": "USED_AFTER",
      "weight": 3.5
    },
    {
      "id": "e_seq_write_after_read",
      "source_id": "tool_graq_write",
      "target_id": "tool_graq_read",
      "relationship": "USED_AFTER",
      "weight": 2.5
    },
    {
      "id": "e_seq_review_after_read",
      "source_id": "tool_graq_review",
      "target_id": "tool_graq_read",
      "relationship": "USED_AFTER",
      "weight": 2.5
    },
    {
      "id": "e_seq_gen_after_review",
      "source_id": "tool_graq_generate",
      "target_id": "tool_graq_review",
      "relationship": "USED_AFTER",
      "weight": 2.0
    },
    {
      "id": "e_seq_preflight_after_imp",
      "source_id": "tool_graq_preflight",
      "target_id": "tool_graq_impact",
      "relationship": "USED_AFTER",
      "weight": 2.5
    },
    {
      "id": "e_seq_gen_after_pre",
      "source_id": "tool_graq_generate",
      "target_id": "tool_graq_preflight",
      "relationship": "USED_AFTER",
      "weight": 2.5
    },
    {
      "id": "e_wf_bf_grep",
      "source_id": "workflow_bug_fix",
      "target_id": "tool_graq_grep",
      "relationship": "PART_OF",
      "weight": 1.0
    },
    {
      "id": "e_wf_bf_read",
      "source_id": "workflow_bug_fix",
      "target_id": "tool_graq_read",
      "relationship": "PART_OF",
      "weight": 1.0
    },
    {
      "id": "e_wf_bf_debug",
      "source_id": "workflow_bug_fix",
      "target_id": "tool_graq_debug",
      "relationship": "PART_OF",
      "weight": 1.0
    },
    {
      "id": "e_wf_bf_gen",
      "source_id": "workflow_bug_fix",
      "target_id": "tool_graq_generate",
      "relationship": "PART_OF",
      "weight": 1.0
    },
    {
      "id": "e_wf_bf_write",
      "source_id": "workflow_bug_fix",
      "target_id": "tool_graq_write",
      "relationship": "PART_OF",
      "weight": 1.0
    },
    {
      "id": "e_wf_bf_test",
      "source_id": "workflow_bug_fix",
      "target_id": "tool_graq_test",
      "relationship": "PART_OF",
      "weight": 1.0
    },
    {
      "id": "e_wf_bf_commit",
      "source_id": "workflow_bug_fix",
      "target_id": "tool_graq_git_commit",
      "relationship": "PART_OF",
      "weight": 1.0
    },
    {
      "id": "e_wf_bf_learn",
      "source_id": "workflow_bug_fix",
      "target_id": "tool_graq_learn",
      "relationship": "PART_OF",
      "weight": 1.0
    },
    {
      "id": "e_wf_sc_ctx",
      "source_id": "workflow_scaffold_and_test",
      "target_id": "tool_graq_context",
      "relationship": "PART_OF",
      "weight": 1.0
    },
    {
      "id": "e_wf_sc_scaf",
      "source_id": "workflow_scaffold_and_test",
      "target_id": "tool_graq_scaffold",
      "relationship": "PART_OF",
      "weight": 1.0
    },
    {
      "id": "e_wf_sc_write",
      "source_id": "workflow_scaffold_and_test",
      "target_id": "tool_graq_write",
      "relationship": "PART_OF",
      "weight": 1.0
    },
    {
      "id": "e_wf_sc_test",
      "source_id": "workflow_scaffold_and_test",
      "target_id": "tool_graq_test",
      "relationship": "PART_OF",
      "weight": 1.0
    },
    {
      "id": "e_wf_sc_learn",
      "source_id": "workflow_scaffold_and_test",
      "target_id": "tool_graq_learn",
      "relationship": "PART_OF",
      "weight": 1.0
    },
    {
      "id": "e_wf_gr_branch",
      "source_id": "workflow_governed_refactor",
      "target_id": "tool_graq_git_branch",
      "relationship": "PART_OF",
      "weight": 1.0
    },
    {
      "id": "e_wf_gr_impact",
      "source_id": "workflow_governed_refactor",
      "target_id": "tool_graq_impact",
      "relationship": "PART_OF",
      "weight": 1.0
    },
    {
      "id": "e_wf_gr_pre",
      "source_id": "workflow_governed_refactor",
      "target_id": "tool_graq_preflight",
      "relationship": "PART_OF",
      "weight": 1.0
    },
    {
      "id": "e_wf_gr_gen",
      "source_id": "workflow_governed_refactor",
      "target_id": "tool_graq_generate",
      "relationship": "PART_OF",
      "weight": 1.0
    },
    {
      "id": "e_wf_gr_write",
      "source_id": "workflow_governed_refactor",
      "target_id": "tool_graq_write",
      "relationship": "PART_OF",
      "weight": 1.0
    },
    {
      "id": "e_wf_gr_test",
      "source_id": "workflow_governed_refactor",
      "target_id": "tool_graq_test",
      "relationship": "PART_OF",
      "weight": 1.0
    },
    {
      "id": "e_wf_gr_gate",
      "source_id": "workflow_governed_refactor",
      "target_id": "tool_graq_gate",
      "relationship": "PART_OF",
      "weight": 1.0
    },
    {
      "id": "e_wf_gr_commit",
      "source_id": "workflow_governed_refactor",
      "target_id": "tool_graq_git_commit",
      "relationship": "PART_OF",
      "weight": 1.0
    },
    {
      "id": "e_wf_rf_read",
      "source_id": "workflow_review_and_fix",
      "target_id": "tool_graq_read",
      "relationship": "PART_OF",
      "weight": 1.0
    },
    {
      "id": "e_wf_rf_review",
      "source_id": "workflow_review_and_fix",
      "target_id": "tool_graq_review",
      "relationship": "PART_OF",
      "weight": 1.0
    },
    {
      "id": "e_wf_rf_gen",
      "source_id": "workflow_review_and_fix",
      "target_id": "tool_graq_generate",
      "relationship": "PART_OF",
      "weight": 1.0
    },
    {
      "id": "e_wf_rf_write",
      "source_id": "workflow_review_and_fix",
      "target_id": "tool_graq_write",
      "relationship": "PART_OF",
      "weight": 1.0
    },
    {
      "id": "e_wf_rf_test",
      "source_id": "workflow_review_and_fix",
      "target_id": "tool_graq_test",
      "relationship": "PART_OF",
      "weight": 1.0
    },
    {
      "id": "e_wf_ci_glob",
      "source_id": "workflow_convention_inference",
      "target_id": "tool_graq_glob",
      "relationship": "PART_OF",
      "weight": 1.0
    },
    {
      "id": "e_wf_ci_read",
      "source_id": "workflow_convention_inference",
      "target_id": "tool_graq_read",
      "relationship": "PART_OF",
      "weight": 1.0
    },
    {
      "id": "e_wf_ci_write",
      "source_id": "workflow_convention_inference",
      "target_id": "tool_graq_write",
      "relationship": "PART_OF",
      "weight": 1.0
    },
    {
      "id": "e_les_sdkhf01_gen",
      "source_id": "lesson_sdk_hf_01",
      "target_id": "tool_graq_generate",
      "relationship": "CAUSED_BY",
      "weight": 1.0
    },
    {
      "id": "e_les_dif01_apply",
      "source_id": "lesson_cg_dif_01",
      "target_id": "tool_graq_apply",
      "relationship": "CAUSED_BY",
      "weight": 1.0
    },
    {
      "id": "e_les_dif01_edit",
      "source_id": "lesson_cg_dif_01",
      "target_id": "tool_graq_edit",
      "relationship": "CAUSED_BY",
      "weight": 1.0
    },
    {
      "id": "e_les_reason02_reason",
      "source_id": "lesson_cg_reason_02",
      "target_id": "tool_graq_reason",
      "relationship": "CAUSED_BY",
      "weight": 1.0
    },
    {
      "id": "e_les_reason01_batch",
      "source_id": "lesson_cg_reason_01",
      "target_id": "tool_graq_reason_batch",
      "relationship": "CAUSED_BY",
      "weight": 1.0
    },
    {
      "id": "e_les_sdkhf02_reason",
      "source_id": "lesson_sdk_hf_02",
      "target_id": "tool_graq_reason",
      "relationship": "CAUSED_BY",
      "weight": 1.0
    },
    {
      "id": "e_les_cold_reason",
      "source_id": "lesson_reason_cold",
      "target_id": "tool_graq_reason",
      "relationship": "CAUSED_BY",
      "weight": 1.0
    },
    {
      "id": "e_les_full_test",
      "source_id": "lesson_pytest_full",
      "target_id": "tool_graq_test",
      "relationship": "CAUSED_BY",
      "weight": 1.0
    },
    {
      "id": "e_les_hub_apply",
      "source_id": "lesson_graq_apply_hub",
      "target_id": "tool_graq_apply",
      "relationship": "CAUSED_BY",
      "weight": 1.0
    },
    {
      "id": "e_les_dry_write",
      "source_id": "lesson_dry_run_first",
      "target_id": "tool_graq_write",
      "relationship": "CAUSED_BY",
      "weight": 1.0
    },
    {
      "id": "e_les_dry_edit",
      "source_id": "lesson_dry_run_first",
      "target_id": "tool_graq_edit",
      "relationship": "CAUSED_BY",
      "weight": 1.0
    },
    {
      "id": "e_les_dry_apply",
      "source_id": "lesson_dry_run_first",
      "target_id": "tool_graq_apply",
      "relationship": "CAUSED_BY",
      "weight": 1.0
    },
    {
      "id": "e_les_ci_write",
      "source_id": "lesson_convention_inf",
      "target_id": "tool_graq_write",
      "relationship": "CAUSED_BY",
      "weight": 1.0
    },
    {
      "id": "e_les_patent_commit",
      "source_id": "lesson_patent_scrub",
      "target_id": "tool_graq_git_commit",
      "relationship": "CAUSED_BY",
      "weight": 1.0
    },
    {
      "id": "e_les_destr_bash",
      "source_id": "lesson_destructive",
      "target_id": "tool_graq_bash",
      "relationship": "CAUSED_BY",
      "weight": 1.0
    },
    {
      "id": "e_les_destr_ingest",
      "source_id": "lesson_destructive",
      "target_id": "tool_graq_ingest",
      "relationship": "CAUSED_BY",
      "weight": 1.0
    },
    {
      "id": "e_les_destr_vendor",
      "source_id": "lesson_destructive",
      "target_id": "tool_graq_vendor",
      "relationship": "CAUSED_BY",
      "weight": 1.0
    },
    {
      "id": "e_les_destr_reload",
      "source_id": "lesson_destructive",
      "target_id": "tool_graq_reload",
      "relationship": "CAUSED_BY",
      "weight": 1.0
    },
    {
      "id": "e_audit_govgate",
      "source_id": "intent_audit",
      "target_id": "tool_graq_gov_gate",
      "relationship": "MATCHES_INTENT",
      "weight": 2.5
    },
    {
      "id": "e_audit_safety",
      "source_id": "intent_audit",
      "target_id": "tool_graq_safety_check",
      "relationship": "MATCHES_INTENT",
      "weight": 2.5
    },
    {
      "id": "e_audit_audit",
      "source_id": "intent_audit",
      "target_id": "tool_graq_audit",
      "relationship": "MATCHES_INTENT",
      "weight": 2.0
    },
    {
      "id": "e_audit_runtime",
      "source_id": "intent_audit",
      "target_id": "tool_graq_runtime",
      "relationship": "MATCHES_INTENT",
      "weight": 2.0
    },
    {
      "id": "e_gref_govgate",
      "source_id": "intent_governed_refactor",
      "target_id": "tool_graq_gov_gate",
      "relationship": "MATCHES_INTENT",
      "weight": 2.0
    },
    {
      "id": "e_review_safety",
      "source_id": "intent_review",
      "target_id": "tool_graq_safety_check",
      "relationship": "MATCHES_INTENT",
      "weight": 2.0
    },
    {
      "id": "e_r2_intent_visual_audit_tool_graq_scorch_a11y",
      "source_id": "intent_visual_audit",
      "target_id": "tool_graq_scorch_a11y",
      "relationship": "MATCHES_INTENT",
      "weight": 2.5
    },
    {
      "id": "e_r2_intent_visual_audit_tool_graq_scorch_perf",
      "source_id": "intent_visual_audit",
      "target_id": "tool_graq_scorch_perf",
      "relationship": "MATCHES_INTENT",
      "weight": 2.5
    },
    {
      "id": "e_r2_intent_visual_audit_tool_graq_scorch_seo",
      "source_id": "intent_visual_audit",
      "target_id": "tool_graq_scorch_seo",
      "relationship": "MATCHES_INTENT",
      "weight": 2.5
    },
    {
      "id": "e_r2_intent_visual_audit_tool_graq_scorch_mobile",
      "source_id": "intent_visual_audit",
      "target_id": "tool_graq_scorch_mobile",
      "relationship": "MATCHES_INTENT",
      "weight": 2.5
    },
    {
      "id": "e_r2_intent_visual_audit_tool_graq_scorch_i18n",
      "source_id": "intent_visual_audit",
      "target_id": "tool_graq_scorch_i18n",
      "relationship": "MATCHES_INTENT",
      "weight": 2.5
    },
    {
      "id": "e_r2_intent_visual_audit_tool_graq_scorch_brand",
      "source_id": "intent_visual_audit",
      "target_id": "tool_graq_scorch_brand",
      "relationship": "MATCHES_INTENT",
      "weight": 2.5
    },
    {
      "id": "e_r2_intent_visual_audit_tool_graq_scorch_security",
      "source_id": "intent_visual_audit",
      "target_id": "tool_graq_scorch_security",
      "relationship": "MATCHES_INTENT",
      "weight": 2.5
    },
    {
      "id": "e_r2_intent_visual_audit_tool_graq_scorch_conversion",
      "source_id": "intent_visual_audit",
      "target_id": "tool_graq_scorch_conversion",
      "relationship": "MATCHES_INTENT",
      "weight": 2.5
    },
    {
      "id": "e_r2_intent_visual_audit_tool_graq_scorch_auth_flow",
      "source_id": "intent_visual_audit",
      "target_id": "tool_graq_scorch_auth_flow",
      "relationship": "MATCHES_INTENT",
      "weight": 2.5
    },
    {
      "id": "e_r2_intent_visual_audit_tool_graq_scorch_behavioral",
      "source_id": "intent_visual_audit",
      "target_id": "tool_graq_scorch_behavioral",
      "relationship": "MATCHES_INTENT",
      "weight": 2.5
    },
    {
      "id": "e_r2_intent_visual_audit_tool_graq_scorch_diff",
      "source_id": "intent_visual_audit",
      "target_id": "tool_graq_scorch_diff",
      "relationship": "MATCHES_INTENT",
      "weight": 2.5
    },
    {
      "id": "e_r2_intent_visual_audit_tool_graq_phantom_audit",
      "source_id": "intent_visual_audit",
      "target_id": "tool_graq_phantom_audit",
      "relationship": "MATCHES_INTENT",
      "weight": 2.5
    },
    {
      "id": "e_r2_intent_visual_audit_tool_graq_phantom_screenshot",
      "source_id": "intent_visual_audit",
      "target_id": "tool_graq_phantom_screenshot",
      "relationship": "MATCHES_INTENT",
      "weight": 2.5
    },
    {
      "id": "e_r2_intent_browser_automation_tool_graq_phantom_click",
      "source_id": "intent_browser_automation",
      "target_id": "tool_graq_phantom_click",
      "relationship": "MATCHES_INTENT",
      "weight": 2.5
    },
    {
      "id": "e_r2_intent_browser_automation_tool_graq_phantom_type",
      "source_id": "intent_browser_automation",
      "target_id": "tool_graq_phantom_type",
      "relationship": "MATCHES_INTENT",
      "weight": 2.5
    },
    {
      "id": "e_r2_intent_browser_automation_tool_graq_phantom_screenshot",
      "source_id": "intent_browser_automation",
      "target_id": "tool_graq_phantom_screenshot",
      "relationship": "MATCHES_INTENT",
      "weight": 2.5
    },
    {
      "id": "e_r2_intent_browser_automation_tool_graq_phantom_flow",
      "source_id": "intent_browser_automation",
      "target_id": "tool_graq_phantom_flow",
      "relationship": "MATCHES_INTENT",
      "weight": 2.5
    },
    {
      "id": "e_r2_intent_browser_automation_tool_graq_phantom_discover",
      "source_id": "intent_browser_automation",
      "target_id": "tool_graq_phantom_discover",
      "relationship": "MATCHES_INTENT",
      "weight": 2.5
    },
    {
      "id": "e_r2_intent_browser_automation_tool_graq_phantom_audit",
      "source_id": "intent_browser_automation",
      "target_id": "tool_graq_phantom_audit",
      "relationship": "MATCHES_INTENT",
      "weight": 2.5
    },
    {
      "id": "e_r2_intent_production_deploy_check_tool_graq_scorch_audit",
      "source_id": "intent_production_deploy_check",
      "target_id": "tool_graq_scorch_audit",
      "relationship": "MATCHES_INTENT",
      "weight": 2.5
    },
    {
      "id": "e_r2_intent_production_deploy_check_tool_graq_scorch_security",
      "source_id": "intent_production_deploy_check",
      "target_id": "tool_graq_scorch_security",
      "relationship": "MATCHES_INTENT",
      "weight": 2.5
    },
    {
      "id": "e_r2_intent_production_deploy_check_tool_graq_scorch_perf",
      "source_id": "intent_production_deploy_check",
      "target_id": "tool_graq_scorch_perf",
      "relationship": "MATCHES_INTENT",
      "weight": 2.5
    },
    {
      "id": "e_r2_intent_production_deploy_check_tool_graq_audit",
      "source_id": "intent_production_deploy_check",
      "target_id": "tool_graq_audit",
      "relationship": "MATCHES_INTENT",
      "weight": 2.5
    },
    {
      "id": "e_r2_intent_production_deploy_check_tool_graq_runtime",
      "source_id": "intent_production_deploy_check",
      "target_id": "tool_graq_runtime",
      "relationship": "MATCHES_INTENT",
      "weight": 2.5
    },
    {
      "id": "e_r2_intent_dependency_management_tool_graq_vendor",
      "source_id": "intent_dependency_management",
      "target_id": "tool_graq_vendor",
      "relationship": "MATCHES_INTENT",
      "weight": 2.5
    },
    {
      "id": "e_r2_intent_dependency_management_tool_graq_ingest",
      "source_id": "intent_dependency_management",
      "target_id": "tool_graq_ingest",
      "relationship": "MATCHES_INTENT",
      "weight": 2.5
    },
    {
      "id": "e_r2_intent_dependency_management_tool_graq_reload",
      "source_id": "intent_dependency_management",
      "target_id": "tool_graq_reload",
      "relationship": "MATCHES_INTENT",
      "weight": 2.5
    },
    {
      "id": "e_r2_intent_autonomous_task_tool_graq_plan",
      "source_id": "intent_autonomous_task",
      "target_id": "tool_graq_plan",
      "relationship": "MATCHES_INTENT",
      "weight": 2.5
    },
    {
      "id": "e_r2_intent_autonomous_task_tool_graq_route",
      "source_id": "intent_autonomous_task",
      "target_id": "tool_graq_route",
      "relationship": "MATCHES_INTENT",
      "weight": 2.5
    },
    {
      "id": "e_r2_intent_autonomous_task_tool_graq_auto",
      "source_id": "intent_autonomous_task",
      "target_id": "tool_graq_auto",
      "relationship": "MATCHES_INTENT",
      "weight": 2.5
    },
    {
      "id": "e_r2_intent_autonomous_task_tool_graq_correct",
      "source_id": "intent_autonomous_task",
      "target_id": "tool_graq_correct",
      "relationship": "MATCHES_INTENT",
      "weight": 2.5
    },
    {
      "id": "e_r2_intent_autonomous_task_tool_graq_workflow",
      "source_id": "intent_autonomous_task",
      "target_id": "tool_graq_workflow",
      "relationship": "MATCHES_INTENT",
      "weight": 2.5
    },
    {
      "id": "e_r2_intent_autonomous_task_tool_graq_todo",
      "source_id": "intent_autonomous_task",
      "target_id": "tool_graq_todo",
      "relationship": "MATCHES_INTENT",
      "weight": 2.5
    },
    {
      "id": "e_r2_intent_knowledge_lookup_tool_graq_lessons",
      "source_id": "intent_knowledge_lookup",
      "target_id": "tool_graq_lessons",
      "relationship": "MATCHES_INTENT",
      "weight": 2.5
    },
    {
      "id": "e_r2_intent_knowledge_lookup_tool_graq_profile",
      "source_id": "intent_knowledge_lookup",
      "target_id": "tool_graq_profile",
      "relationship": "MATCHES_INTENT",
      "weight": 2.5
    },
    {
      "id": "e_r2_intent_knowledge_lookup_tool_graq_web_search",
      "source_id": "intent_knowledge_lookup",
      "target_id": "tool_graq_web_search",
      "relationship": "MATCHES_INTENT",
      "weight": 2.5
    },
    {
      "id": "e_r2_intent_knowledge_lookup_tool_graq_git_log",
      "source_id": "intent_knowledge_lookup",
      "target_id": "tool_graq_git_log",
      "relationship": "MATCHES_INTENT",
      "weight": 2.5
    },
    {
      "id": "e_r2_intent_knowledge_lookup_tool_graq_todo",
      "source_id": "intent_knowledge_lookup",
      "target_id": "tool_graq_todo",
      "relationship": "MATCHES_INTENT",
      "weight": 2.5
    },
    {
      "id": "e_r2_intent_review_pr_tool_graq_github_pr",
      "source_id": "intent_review_pr",
      "target_id": "tool_graq_github_pr",
      "relationship": "MATCHES_INTENT",
      "weight": 2.5
    },
    {
      "id": "e_r2_intent_review_pr_tool_graq_github_diff",
      "source_id": "intent_review_pr",
      "target_id": "tool_graq_github_diff",
      "relationship": "MATCHES_INTENT",
      "weight": 2.5
    },
    {
      "id": "e_r2_intent_review_pr_tool_graq_reason_batch",
      "source_id": "intent_review_pr",
      "target_id": "tool_graq_reason_batch",
      "relationship": "MATCHES_INTENT",
      "weight": 2.5
    },
    {
      "id": "e_r2_intent_trace_reasoning_tool_graq_drace",
      "source_id": "intent_trace_reasoning",
      "target_id": "tool_graq_drace",
      "relationship": "MATCHES_INTENT",
      "weight": 2.5
    },
    {
      "id": "e_r2_intent_trace_reasoning_tool_graq_reason_batch",
      "source_id": "intent_trace_reasoning",
      "target_id": "tool_graq_reason_batch",
      "relationship": "MATCHES_INTENT",
      "weight": 2.5
    },
    {
      "id": "e_r2_intent_trace_reasoning_tool_graq_predict",
      "source_id": "intent_trace_reasoning",
      "target_id": "tool_graq_predict",
      "relationship": "MATCHES_INTENT",
      "weight": 2.5
    },
    {
      "id": "e_r2_intent_trace_reasoning_tool_graq_lifecycle",
      "source_id": "intent_trace_reasoning",
      "target_id": "tool_graq_lifecycle",
      "relationship": "MATCHES_INTENT",
      "weight": 2.5
    },
    {
      "id": "e_r2_intent_refactor_tool_graq_edit",
      "source_id": "intent_refactor",
      "target_id": "tool_graq_edit",
      "relationship": "MATCHES_INTENT",
      "weight": 2.0
    },
    {
      "id": "e_r2_intent_bug_fix_tool_graq_bash",
      "source_id": "intent_bug_fix",
      "target_id": "tool_graq_bash",
      "relationship": "MATCHES_INTENT",
      "weight": 2.0
    },
    {
      "id": "e_r2_intent_git_status_tool_graq_git_log",
      "source_id": "intent_git_status",
      "target_id": "tool_graq_git_log",
      "relationship": "MATCHES_INTENT",
      "weight": 2.0
    },
    {
      "id": "e_r2_intent_commit_tool_graq_git_log",
      "source_id": "intent_commit",
      "target_id": "tool_graq_git_log",
      "relationship": "MATCHES_INTENT",
      "weight": 2.0
    },
    {
      "id": "e_r2_intent_visual_audit_tool_graq_phantom_session",
      "source_id": "intent_visual_audit",
      "target_id": "tool_graq_phantom_session",
      "relationship": "MATCHES_INTENT",
      "weight": 3.0
    },
    {
      "id": "e_r2_intent_visual_audit_tool_graq_phantom_browse",
      "source_id": "intent_visual_audit",
      "target_id": "tool_graq_phantom_browse",
      "relationship": "MATCHES_INTENT",
      "weight": 3.0
    },
    {
      "id": "e_r2_intent_visual_audit_tool_graq_scorch_audit",
      "source_id": "intent_visual_audit",
      "target_id": "tool_graq_scorch_audit",
      "relationship": "MATCHES_INTENT",
      "weight": 3.0
    },
    {
      "id": "e_r2_intent_visual_audit_tool_graq_scorch_report",
      "source_id": "intent_visual_audit",
      "target_id": "tool_graq_scorch_report",
      "relationship": "MATCHES_INTENT",
      "weight": 3.0
    },
    {
      "id": "e_r2_intent_browser_automation_tool_graq_phantom_session",
      "source_id": "intent_browser_automation",
      "target_id": "tool_graq_phantom_session",
      "relationship": "MATCHES_INTENT",
      "weight": 3.0
    },
    {
      "id": "e_r2_intent_browser_automation_tool_graq_phantom_browse",
      "source_id": "intent_browser_automation",
      "target_id": "tool_graq_phantom_browse",
      "relationship": "MATCHES_INTENT",
      "weight": 3.0
    },
    {
      "id": "e_r2_intent_production_deploy_check_tool_graq_phantom_browse",
      "source_id": "intent_production_deploy_check",
      "target_id": "tool_graq_phantom_browse",
      "relationship": "MATCHES_INTENT",
      "weight": 3.0
    },
    {
      "id": "e_r2_intent_review_pr_tool_graq_review",
      "source_id": "intent_review_pr",
      "target_id": "tool_graq_review",
      "relationship": "MATCHES_INTENT",
      "weight": 3.0
    }
  ]
}
