{
  "module": "graqle.cloud.gateway",
  "files": [
    "graqle/cloud/gateway.py"
  ],
  "node_count": 13,
  "function_count": 9,
  "class_count": 3,
  "line_count": 0,
  "public_interfaces": [
    {
      "name": "value_prop",
      "type": "Function",
      "line": 139
    },
    {
      "name": "check_upsell_triggers",
      "type": "Function",
      "line": 141
    },
    {
      "name": "is_connected",
      "type": "Function",
      "line": 233
    },
    {
      "name": "get_status",
      "type": "Function",
      "line": 235
    },
    {
      "name": "push_delta",
      "type": "Function",
      "line": 249
    },
    {
      "name": "pull_delta",
      "type": "Function",
      "line": 270
    },
    {
      "name": "register_team",
      "type": "Function",
      "line": 287
    },
    {
      "name": "get_observability",
      "type": "Function",
      "line": 302
    },
    {
      "name": "CloudServiceStatus",
      "type": "Class",
      "line": 37
    },
    {
      "name": "UpsellTrigger",
      "type": "Class",
      "line": 130
    },
    {
      "name": "CloudGateway",
      "type": "Class",
      "line": 220
    }
  ],
  "consumers": [
    {
      "module": "tests.test_cloud.test_gateway",
      "via": "IMPORTS"
    }
  ],
  "dependencies": [
    {
      "module": "__future__",
      "type": "external"
    },
    {
      "module": "json",
      "type": "external"
    },
    {
      "module": "logging",
      "type": "external"
    },
    {
      "module": "dataclasses",
      "type": "external"
    },
    {
      "module": "typing",
      "type": "external"
    }
  ],
  "risk_score": 0.218,
  "risk_level": "LOW",
  "impact_radius": 1,
  "chunk_coverage": 100.0,
  "description_coverage": 100.0,
  "constraints": [],
  "incidents": [],
  "last_compiled": "2026-03-15T22:41:29.198353+00:00"
}