{
  "module": "graqle.ontology.router",
  "files": [
    "graqle/ontology/router.py"
  ],
  "node_count": 8,
  "function_count": 6,
  "class_count": 1,
  "line_count": 0,
  "public_interfaces": [
    {
      "name": "stats",
      "type": "Function",
      "line": 42
    },
    {
      "name": "set_registry",
      "type": "Function",
      "line": 44
    },
    {
      "name": "get_valid_recipients",
      "type": "Function",
      "line": 48
    },
    {
      "name": "reset_stats",
      "type": "Function",
      "line": 152
    },
    {
      "name": "OntologyRouter",
      "type": "Class",
      "line": 28
    }
  ],
  "consumers": [
    {
      "module": "graqle.ontology.__init__",
      "via": "IMPORTS"
    },
    {
      "module": "tests.test_ontology.test_router",
      "via": "IMPORTS"
    },
    {
      "module": "tests.test_scanner.test_nl_router",
      "via": "IMPORTS"
    }
  ],
  "dependencies": [
    {
      "module": "__future__",
      "type": "external"
    },
    {
      "module": "logging",
      "type": "external"
    },
    {
      "module": "typing",
      "type": "external"
    }
  ],
  "risk_score": 0.199,
  "risk_level": "LOW",
  "impact_radius": 3,
  "chunk_coverage": 100.0,
  "description_coverage": 100.0,
  "constraints": [],
  "incidents": [],
  "last_compiled": "2026-03-15T22:41:29.126237+00:00"
}